{
  "posts": [
    {
      "id": 1,
      "title": "json-server",
      "author": "typicode"
    },
    {
      "title": "nanananaBatman",
      "author": "DICK",
      "id": 3
    },
    {
      "title": "德玛西亚",
      "author": "alfred",
      "id": 4
    },
    {
      "title": "德玛西亚",
      "author": "alfred",
      "id": 5
    },
    {
      "title": "nanananaBatman",
      "author": "nightwing",
      "id": 6
    },
    {
      "title": "nanananaBatman",
      "author": "nightwing",
      "id": 7
    },
    {
      "title": "nanananaBatman",
      "author": "nightwing",
      "id": 8
    },
    {
      "title": "nanananaBatman",
      "author": "nightwing",
      "id": 9
    }
  ],
  "comments": [
    {
      "id": 1,
      "body": "some comment",
      "postId": 1
    }
  ],
  "profile": {
    "name": "typicode"
  }
}